outly/__init__.py
outly/detectors.py
outly/utils.py
outly-0.1.0.dist-info/licenses/LICENSE
outly-0.1.0.dist-info/METADATA
outly-0.1.0.dist-info/WHEEL
outly-0.1.0.dist-info/top_level.txt
outly-0.1.0.dist-info/RECORD
