Metadata-Version: 2.4
Name: outly
Version: 0.1.0
Summary: Detección de outliers en Python con métodos estadísticos (Z-score e IQR).
Home-page: https://github.com/josuemzx/outly
Author: ESAI JOSUE HUAMAN MEZA
Author-email: esai.huaman@gmail.com
License: MIT
Classifier: Programming Language :: Python :: 3
Classifier: License :: OSI Approved :: MIT License
Classifier: Operating System :: OS Independent
Requires-Python: >=3.7
License-File: LICENSE
Requires-Dist: numpy>=1.17.0
Dynamic: author
Dynamic: author-email
Dynamic: classifier
Dynamic: description
Dynamic: description-content-type
Dynamic: home-page
Dynamic: license
Dynamic: license-file
Dynamic: requires-dist
Dynamic: requires-python
Dynamic: summary
